[
  {
    "codigo": 2,
    "marca": "marcsdfdfghdfgh",
    "precio": 84444,
    "path": "fotos/2.jpg"
  },
  {
    "codigo": 1,
    "marca": "marca_cuatro",
    "precio": 400,
    "path": "fotos/1.jpg"
  },
  {
    "codigo": 1762816270023,
    "marca": "rwerw",
    "precio": 12342313123,
    "categoria": "Deporte",
    "path": "img/default.jpg"
  },
  {
    "codigo": 1762816278703,
    "marca": "rwerw",
    "precio": 12342313123,
    "categoria": "Deporte",
    "path": "img/default.jpg"
  },
  {
    "codigo": 1762860735044,
    "marca": "abc",
    "precio": 123,
    "categoria": "Categoría 1",
    "path": "img/default.jpg"
  }
]